flask_cli/__init__.py
flask_cli/_compat.py
flask_cli/app.py
flask_cli/cli.py
flask_cli/ext.py
flask_cli/helpers.py
flask_cli/version.py
Flask_CLI-0.4.0.dist-info/top_level.txt
Flask_CLI-0.4.0.dist-info/entry_points.txt
Flask_CLI-0.4.0.dist-info/METADATA
Flask_CLI-0.4.0.dist-info/DESCRIPTION.rst
Flask_CLI-0.4.0.dist-info/metadata.json
Flask_CLI-0.4.0.dist-info/WHEEL
Flask_CLI-0.4.0.dist-info/RECORD
