Metadata-Version: 1.1
Name: Flask-CLI
Version: 0.4.0
Summary: Backport of Flask 1.0 new click integration.
Home-page: http://github.com/inveniosoftware/flask-cli/
Author: Invenio Collaboration
Author-email: info@invenio-software.org
License: BSD
Platform: any
Classifier: Programming Language :: Python :: 2
Classifier: Programming Language :: Python :: 2.6
Classifier: Programming Language :: Python :: 2.7
Classifier: Programming Language :: Python :: 3
Classifier: Programming Language :: Python :: 3.3
Classifier: Programming Language :: Python :: 3.4
Classifier: Programming Language :: Python :: 3.5
Classifier: Topic :: Utilities
Classifier: Development Status :: 5 - Production/Stable
